LICENSE
README.md
setup.py
calkeeper/__init__.py
calkeeper.egg-info/PKG-INFO
calkeeper.egg-info/SOURCES.txt
calkeeper.egg-info/dependency_links.txt
calkeeper.egg-info/top_level.txt
calkeeper.egg-info/zip-safe